regrippy/__init__.py
regrippy/plugins/__init__.py
regrippy/plugins/antivirus.py
regrippy/plugins/auditpol.py
regrippy/plugins/compname.py
regrippy/plugins/env.py
regrippy/plugins/filedialogmru.py
regrippy/plugins/gpo.py
regrippy/plugins/kb.py
regrippy/plugins/keyboard.py
regrippy/plugins/lastloggedon.py
regrippy/plugins/lastshutdown.py
regrippy/plugins/localgroups.py
regrippy/plugins/localusers.py
regrippy/plugins/mndmru.py
regrippy/plugins/mstscmru.py
regrippy/plugins/office_macros.py
regrippy/plugins/portproxy.py
regrippy/plugins/printer_history.py
regrippy/plugins/printer_ports.py
regrippy/plugins/proxy.py
regrippy/plugins/putty.py
regrippy/plugins/rdphint.py
regrippy/plugins/recentdocs.py
regrippy/plugins/regtime.py
regrippy/plugins/run.py
regrippy/plugins/runmru.py
regrippy/plugins/services.py
regrippy/plugins/shimcache.py
regrippy/plugins/srum.py
regrippy/plugins/sysinternals.py
regrippy/plugins/systeminfo.py
regrippy/plugins/tasks.py
regrippy/plugins/teamviewer.py
regrippy/plugins/timezone.py
regrippy/plugins/typedurls.py
regrippy/plugins/uninstall.py
regrippy/plugins/usb.py
regrippy/plugins/userassist.py
regrippy/plugins/usersids.py
regrippy/plugins/version.py
regrippy/thirdparty/ShimCacheParser.py
regrippy/thirdparty/__init__.py
regrippy-2.0.2.data/scripts/regrip.py
regrippy-2.0.2.dist-info/licenses/LICENSE
regrippy-2.0.2.dist-info/METADATA
regrippy-2.0.2.dist-info/WHEEL
regrippy-2.0.2.dist-info/entry_points.txt
regrippy-2.0.2.dist-info/top_level.txt
regrippy-2.0.2.dist-info/RECORD
