Metadata-Version: 2.4
Name: regrippy
Version: 2.0.2
Summary: A modern Python-3-based alternative to RegRipper
Home-page: https://github.com/airbus-cert/regrippy
Author: Airbus CERT
Author-email: cert@airbus.com
Classifier: Programming Language :: Python
Classifier: Programming Language :: Python :: 3
Classifier: Programming Language :: Python :: 3 :: Only
Classifier: Environment :: Console
Classifier: Operating System :: OS Independent
Classifier: License :: OSI Approved :: Apache Software License
Classifier: Topic :: Utilities
Classifier: Intended Audience :: Information Technology
Requires-Python: >=3.7
License-File: LICENSE
Requires-Dist: wheel
Requires-Dist: python-registry>1.1.0
Requires-Dist: importlib_resources
Dynamic: author
Dynamic: author-email
Dynamic: classifier
Dynamic: description
Dynamic: description-content-type
Dynamic: home-page
Dynamic: license-file
Dynamic: requires-dist
Dynamic: requires-python
Dynamic: summary
